{
	"a-icon/type": {
		"description": "图标类型。遵循图标的命名规范",
		"optionType": "string",
		"defaultValue": "-"
	},
	"a-icon/style": {
		"description": "设置图标的样式，例如 fontSize 和 color",
		"optionType": "CSSProperties",
		"defaultValue": "-"
	},
	"a-icon/theme": {
		"options": [
			"filled",
			"outlined",
			"twoTone"
		],
		"description": "图标主题风格。可选实心、描线、双色等主题风格，适用于官方图标",
		"optionType": "'filled' | 'outlined' | 'twoTone'",
		"defaultValue": "'outlined'"
	},
	"a-icon/spin": {
		"description": "是否有旋转动画",
		"optionType": "boolean",
		"defaultValue": "false"
	},
	"a-icon/rotate": {
		"description": "图标旋转角度（1.4.0 后新增，IE9 无效）",
		"optionType": "number",
		"defaultValue": "-"
	},
	"a-icon/component": {
		"description": "控制如何渲染图标，通常是一个渲染根标签为 <svg> 的 Vue 组件，会使 type 属性失效",
		"optionType": "ComponentType<CustomIconComponentProps>",
		"defaultValue": "-"
	},
	"a-icon/twoToneColor": {
		"description": "仅适用双色图标。设置双色图标的主要颜色",
		"optionType": "string (十六进制颜色)",
		"defaultValue": "-"
	}
}